{
    "name": "Default",
    "cycles": [
        {
            "algorithm": "kitt",
            "seconds_in_cycle": 600,
            "options": {
                "color": [0, 1, 1],
                "speed": 4,
                "fade_time": 2,
                "width": 4,
                "border": 20
            }
        },
        {
            "algorithm": "two_color_wave",
            "seconds_in_cycle": 600,
            "options": {
                "colors": [
                    [0.989, 0.88, 0.92],
                    [0.886, 0.29, 1.0]
                ],
                "wavelength": 10,
                "reverse": true,
                "split": true,
                "speed": 4
            }
        },
        {
            "algorithm": "rainbow",
            "seconds_in_cycle": 120,
            "options": {
                "speed": 100,
                "reverse": false
            }
        },
        {
            "algorithm": "split_rainbow",
            "seconds_in_cycle": 120,
            "options": {
                "speed": 100,
                "reverse": false
            }
        }
    ]
}
